Metadata-Version: 1.0
Name: djangosampler
Version: 0.6.0
Summary: Samples a percentage of SQL queries and groups them together for easy viewing
Home-page: https://github.com/colinhowe/djangosampler
Author: Colin Howe
Author-email: colin@colinhowe.co.uk
License: Apache 2.0
Platform: UNKNOWN
Classifier: Development Status :: 4 - Beta
Classifier: Environment :: Web Environment
Classifier: Framework :: Django
Classifier: Intended Audience :: Developers
Classifier: License :: OSI Approved :: Apache Software License
Classifier: Operating System :: OS Independent
Classifier: Programming Language :: Python
Classifier: Topic :: Software Development :: Libraries :: Python Modules
